src/__init__.py
src/configuration.py
src/document_visualizer.py
src/dynamo_gateway.py
src/dyno.py
src/resources.py
dynamocli-0.0.11.dist-info/LICENSE
dynamocli-0.0.11.dist-info/METADATA
dynamocli-0.0.11.dist-info/WHEEL
dynamocli-0.0.11.dist-info/entry_points.txt
dynamocli-0.0.11.dist-info/top_level.txt
dynamocli-0.0.11.dist-info/RECORD
