Metadata-Version: 2.1
Name: dynamocli
Version: 0.0.11
Summary: Command line interface for interacting with a DynamoDB instance
Author: Viktor Blidh
Author-email: viktor.blidh@gmail.com
Requires-Python: >=3.8
License-File: LICENSE
Requires-Dist: boto3
Requires-Dist: rich
Requires-Dist: appdirs
